{
  "entities": [
    {
      "entity_id": "ent_00001",
      "source_file": "Structural_ST07_HexTube.dxf",
      "entity_type": "LWPOLYLINE",
      "handle": "8E",
      "layer": "GEOMETRY",
      "linetype": "BYLAYER",
      "color": 256,
      "geometry": {
        "points": [
          [
            150.0,
            128.86751345948127
          ],
          [
            100.0,
            157.73502691896257
          ],
          [
            50.0,
            128.86751345948127
          ],
          [
            50.00000000000001,
            71.1324865405187
          ],
          [
            99.99999999999999,
            42.264973081037425
          ],
          [
            150.0,
            71.13248654051868
          ]
        ],
        "closed": true,
        "has_arcs": false
      },
      "supported": true,
      "possible_overlap": false,
      "overlap_confidence": 0.0
    },
    {
      "entity_id": "ent_00002",
      "source_file": "Structural_ST07_HexTube.dxf",
      "entity_type": "LWPOLYLINE",
      "handle": "8F",
      "layer": "GEOMETRY",
      "linetype": "BYLAYER",
      "color": 256,
      "geometry": {
        "points": [
          [
            140.0,
            123.09401076758502
          ],
          [
            100.0,
            146.18802153517007
          ],
          [
            60.0,
            123.09401076758502
          ],
          [
            60.00000000000001,
            76.90598923241497
          ],
          [
            99.99999999999999,
            53.81197846482994
          ],
          [
            140.0,
            76.90598923241495
          ]
        ],
        "closed": true,
        "has_arcs": false
      },
      "supported": true,
      "possible_overlap": false,
      "overlap_confidence": 0.0
    },
    {
      "entity_id": "ent_00003",
      "source_file": "Structural_ST07_HexTube.dxf",
      "entity_type": "LINE",
      "handle": "90",
      "layer": "CENTERLINES",
      "linetype": "BYLAYER",
      "color": 256,
      "geometry": {
        "start": [
          30.0,
          100.0
        ],
        "end": [
          170.0,
          100.0
        ],
        "length": 140.0
      },
      "supported": true,
      "possible_overlap": false,
      "overlap_confidence": 0.0
    },
    {
      "entity_id": "ent_00004",
      "source_file": "Structural_ST07_HexTube.dxf",
      "entity_type": "LINE",
      "handle": "91",
      "layer": "CENTERLINES",
      "linetype": "BYLAYER",
      "color": 256,
      "geometry": {
        "start": [
          100.0,
          30.0
        ],
        "end": [
          100.0,
          170.0
        ],
        "length": 140.0
      },
      "supported": true,
      "possible_overlap": false,
      "overlap_confidence": 0.0
    },
    {
      "entity_id": "ent_00005",
      "source_file": "Structural_ST07_HexTube.dxf",
      "entity_type": "DIMENSION",
      "handle": "92",
      "layer": "DIMENSIONS",
      "linetype": "BYLAYER",
      "color": 256,
      "geometry": {
        "dimension_type": "linear",
        "value": 100.0,
        "text": "100mm ACROSS FLATS",
        "position": [
          50.0,
          10.0
        ],
        "target_points": [
          [
            50.0,
            100.0
          ],
          [
            150.0,
            100.0
          ],
          [
            0.0,
            0.0
          ],
          [
            0.0,
            0.0
          ]
        ]
      },
      "supported": true,
      "possible_overlap": false,
      "overlap_confidence": 0.0
    },
    {
      "entity_id": "ent_00006",
      "source_file": "Structural_ST07_HexTube.dxf",
      "entity_type": "DIMENSION",
      "handle": "A1",
      "layer": "DIMENSIONS",
      "linetype": "BYLAYER",
      "color": 256,
      "geometry": {
        "dimension_type": "linear",
        "value": 80.0,
        "text": "80mm INNER FLATS",
        "position": [
          60.0,
          190.0
        ],
        "target_points": [
          [
            60.0,
            100.0
          ],
          [
            140.0,
            100.0
          ],
          [
            0.0,
            0.0
          ],
          [
            0.0,
            0.0
          ]
        ]
      },
      "supported": true,
      "possible_overlap": false,
      "overlap_confidence": 0.0
    },
    {
      "entity_id": "ent_00007",
      "source_file": "Structural_ST07_HexTube.dxf",
      "entity_type": "DIMENSION",
      "handle": "B0",
      "layer": "DIMENSIONS",
      "linetype": "BYLAYER",
      "color": 256,
      "geometry": {
        "dimension_type": "linear",
        "value": 10.0,
        "text": "10mm WALL THICKNESS",
        "position": [
          140.0,
          100.0
        ],
        "target_points": [
          [
            140.0,
            100.0
          ],
          [
            150.0,
            100.0
          ],
          [
            0.0,
            0.0
          ],
          [
            0.0,
            0.0
          ]
        ]
      },
      "supported": true,
      "possible_overlap": false,
      "overlap_confidence": 0.0
    }
  ],
  "quarantined_entities": [],
  "removed_entities": [],
  "filter_reports": [
    {
      "filter": "TextFilter",
      "statistics": {
        "input_entities": 7,
        "kept_entities": 7,
        "quarantined_entities": 0,
        "removed_entities": 0
      }
    },
    {
      "filter": "DegenerateFilter",
      "statistics": {
        "input_entities": 7,
        "kept_entities": 7,
        "quarantined_entities": 0,
        "removed_entities": 0
      }
    },
    {
      "filter": "DuplicateFilter",
      "statistics": {
        "input_entities": 7,
        "kept_entities": 7,
        "quarantined_entities": 0,
        "removed_entities": 0
      }
    },
    {
      "filter": "LayerFilter",
      "statistics": {
        "input_entities": 7,
        "kept_entities": 7,
        "quarantined_entities": 0,
        "removed_entities": 0
      }
    },
    {
      "filter": "BorderFilter",
      "statistics": {
        "input_entities": 7,
        "kept_entities": 7,
        "quarantined_entities": 0,
        "removed_entities": 0
      }
    }
  ]
}