{
  "confidence": {
    "confidence_scores": [
      {
        "candidate_id": "sc_00001",
        "candidate_type": "slot",
        "structural_confidence": 0.6,
        "confidence_factors": {
          "moderate_aspect": true,
          "closed_contour": true
        }
      },
      {
        "candidate_id": "sc_00002",
        "candidate_type": "slot",
        "structural_confidence": 0.6,
        "confidence_factors": {
          "moderate_aspect": true,
          "closed_contour": true
        }
      },
      {
        "candidate_id": "sc_00003",
        "candidate_type": "slot",
        "structural_confidence": 0.6,
        "confidence_factors": {
          "moderate_aspect": true,
          "closed_contour": true
        }
      },
      {
        "candidate_id": "sc_00004",
        "candidate_type": "slot",
        "structural_confidence": 0.6,
        "confidence_factors": {
          "moderate_aspect": true,
          "closed_contour": true
        }
      },
      {
        "candidate_id": "sc_00005",
        "candidate_type": "slot",
        "structural_confidence": 0.6,
        "confidence_factors": {
          "moderate_aspect": true,
          "closed_contour": true
        }
      },
      {
        "candidate_id": "sc_00006",
        "candidate_type": "slot",
        "structural_confidence": 0.6,
        "confidence_factors": {
          "moderate_aspect": true,
          "closed_contour": true
        }
      },
      {
        "candidate_id": "sc_00007",
        "candidate_type": "slot",
        "structural_confidence": 0.6,
        "confidence_factors": {
          "moderate_aspect": true,
          "closed_contour": true
        }
      },
      {
        "candidate_id": "sc_00008",
        "candidate_type": "slot",
        "structural_confidence": 0.6,
        "confidence_factors": {
          "moderate_aspect": true,
          "closed_contour": true
        }
      },
      {
        "candidate_id": "sc_00009",
        "candidate_type": "slot",
        "structural_confidence": 0.6,
        "confidence_factors": {
          "moderate_aspect": true,
          "closed_contour": true
        }
      },
      {
        "candidate_id": "sc_00010",
        "candidate_type": "slot",
        "structural_confidence": 0.6,
        "confidence_factors": {
          "moderate_aspect": true,
          "closed_contour": true
        }
      }
    ],
    "statistics": {
      "total_scored": 10,
      "average_confidence": 0.6,
      "high_confidence": 0,
      "medium_confidence": 10,
      "low_confidence": 0
    }
  },
  "hierarchy": {
    "hierarchy_nodes": [],
    "root_candidates": [],
    "statistics": {
      "total_nodes": 0,
      "root_count": 0,
      "max_depth": 0,
      "pattern_children": 0
    }
  },
  "conflicts": {
    "conflicts": [],
    "conflict_free_entities": 10,
    "statistics": {
      "total_conflicts": 0,
      "high_severity": 0,
      "medium_severity": 0,
      "low_severity": 0,
      "conflict_free_entities": 10,
      "total_claimed_entities": 10
    }
  },
  "repetitions": {
    "repetition_groups": [
      {
        "group_id": "rep_00001",
        "signature": "slot:(6.0, 16.0)",
        "candidate_ids": [
          "sc_00001",
          "sc_00002",
          "sc_00003",
          "sc_00004",
          "sc_00005",
          "sc_00006",
          "sc_00007",
          "sc_00008",
          "sc_00009",
          "sc_00010"
        ],
        "repetition_count": 10,
        "candidate_type": "slot"
      }
    ],
    "unique_candidates": [],
    "statistics": {
      "total_repetition_groups": 1,
      "total_repeated_candidates": 10,
      "total_unique_candidates": 0,
      "max_repetition": 10
    }
  },
  "ambiguity": {
    "ambiguous_candidates": [],
    "ambiguity_summary": {
      "total_ambiguous": 0,
      "by_reason": {},
      "ambiguity_ratio": 0.0
    },
    "statistics": {
      "total_ambiguous": 0,
      "total_candidates_analyzed": 10,
      "ambiguity_threshold": 0.5,
      "ambiguity_ratio": 0.0
    }
  },
  "statistics": {
    "confidence": {
      "total_scored": 10,
      "average_confidence": 0.6,
      "high_confidence": 0,
      "medium_confidence": 10,
      "low_confidence": 0
    },
    "hierarchy": {
      "total_nodes": 0,
      "root_count": 0,
      "max_depth": 0,
      "pattern_children": 0
    },
    "conflicts": {
      "total_conflicts": 0,
      "high_severity": 0,
      "medium_severity": 0,
      "low_severity": 0,
      "conflict_free_entities": 10,
      "total_claimed_entities": 10
    },
    "repetitions": {
      "total_repetition_groups": 1,
      "total_repeated_candidates": 10,
      "total_unique_candidates": 0,
      "max_repetition": 10
    },
    "ambiguity": {
      "total_ambiguous": 0,
      "total_candidates_analyzed": 10,
      "ambiguity_threshold": 0.5,
      "ambiguity_ratio": 0.0
    }
  }
}